[
  {
    "teaName": "Морозний Пік",
    "description": "Чай с ярким, освежающим вкусом и ароматом.",
    "image": "Изображение отсутствует.",
    "category": "Зеленый чай",
    "originCountry": "Китай",
    "teaStockInGrams": 1890,
    "deliveryPricePerGramInDollars": 0.008302,
    "purchasePricePerGramInChinaInDollars": 0.018695,
    "costPricePerGram": 0.026997,
    "salePriceInUkrainePerGramInDollars": 0.10256
  },
  {
    "teaName": "Фіолетова цегла",
    "description": "Описание отсутствует.",
    "image": "Изображение отсутствует.",
    "category": "Неизвестно",
    "originCountry": "Страна происхождения отсутствует.",
    "teaStockInGrams": 2250,
    "deliveryPricePerGramInDollars": 0.008302,
    "purchasePricePerGramInChinaInDollars": 0.029676,
    "costPricePerGram": 0.037978,
    "salePriceInUkrainePerGramInDollars": 0.0984
  },
  {
    "teaName": "Феникс 803 та 8502",
    "description": "Описание отсутствует.",
    "image": "Изображение отсутствует.",
    "category": "Неизвестно",
    "originCountry": "Страна происхождения отсутствует.",
    "teaStockInGrams": 1800,
    "deliveryPricePerGramInDollars": 0.008302,
    "purchasePricePerGramInChinaInDollars": 0.02631,
    "costPricePerGram": 0.034612,
    "salePriceInUkrainePerGramInDollars": 0.0923
  },
  {
    "teaName": "Шен Пуер Цан Ейр",
    "description": "Описание отсутствует.",
    "image": "Изображение отсутствует.",
    "category": "Неизвестно",
    "originCountry": "Страна происхождения отсутствует.",
    "teaStockInGrams": 200,
    "deliveryPricePerGramInDollars": 0.008302,
    "purchasePricePerGramInChinaInDollars": 0.01725,
    "costPricePerGram": 0.025552,
    "salePriceInUkrainePerGramInDollars": 0.07541
  },
  {
    "teaName": "Я бао",
    "description": "Описание отсутствует.",
    "image": "Изображение отсутствует.",
    "category": "Неизвестно",
    "originCountry": "Страна происхождения отсутствует.",
    "teaStockInGrams": 1325,
    "deliveryPricePerGramInDollars": 0.008302,
    "purchasePricePerGramInChinaInDollars": 0.018695,
    "costPricePerGram": 0.026997,
    "salePriceInUkrainePerGramInDollars": 0.05896
  },
  {
    "teaName": "Білий Пуер Місячний Світ",
    "description": "Описание отсутствует.",
    "image": "Изображение отсутствует.",
    "category": "Неизвестно",
    "originCountry": "Страна происхождения отсутствует.",
    "teaStockInGrams": 1000,
    "deliveryPricePerGramInDollars": 0.008302,
    "purchasePricePerGramInChinaInDollars": 0.0302,
    "costPricePerGram": 0.038502,
    "salePriceInUkrainePerGramInDollars": 0.0846
  },
  {
    "teaName": "Місячний Світ от Цайченг",
    "description": "Описание отсутствует.",
    "image": "Изображение отсутствует.",
    "category": "Неизвестно",
    "originCountry": "Страна происхождения отсутствует.",
    "teaStockInGrams": 1877,
    "deliveryPricePerGramInDollars": 0.008302,
    "purchasePricePerGramInChinaInDollars": 0.02344,
    "costPricePerGram": 0.031742,
    "salePriceInUkrainePerGramInDollars": 0.07179
  },
  {
    "teaName": "Тайванський Молочный Улун",
    "description": "Описание отсутствует.",
    "image": "Изображение отсутствует.",
    "category": "Неизвестно",
    "originCountry": "Страна происхождения отсутствует.",
    "teaStockInGrams": 2383,
    "deliveryPricePerGramInDollars": 0.008302,
    "purchasePricePerGramInChinaInDollars": 0.010928,
    "costPricePerGram": 0.01923,
    "salePriceInUkrainePerGramInDollars": 0.082
  },
  {
    "teaName": "Те Гуань Інь Мао Ча",
    "description": "Описание отсутствует.",
    "image": "Изображение отсутствует.",
    "category": "Неизвестно",
    "originCountry": "Страна происхождения отсутствует.",
    "teaStockInGrams": 1410,
    "deliveryPricePerGramInDollars": 0.008302,
    "purchasePricePerGramInChinaInDollars": 0.01772,
    "costPricePerGram": 0.026022,
    "salePriceInUkrainePerGramInDollars": 0.0769
  },
  {
    "teaName": "Те Гуань Інь Тан Бей Сяо Чжен",
    "description": "Описание отсутствует.",
    "image": "Изображение отсутствует.",
    "category": "Неизвестно",
    "originCountry": "Страна происхождения отсутствует.",
    "teaStockInGrams": 493,
    "deliveryPricePerGramInDollars": 0.008302,
    "purchasePricePerGramInChinaInDollars": 0.02738,
    "costPricePerGram": 0.035682,
    "salePriceInUkrainePerGramInDollars": 0.1
  },
  {
    "teaName": "Ку Гуа Те Гуань Инь улун",
    "description": "Описание отсутствует.",
    "image": "Изображение отсутствует.",
    "category": "Неизвестно",
    "originCountry": "Страна происхождения отсутствует.",
    "teaStockInGrams": 440,
    "deliveryPricePerGramInDollars": 0.008302,
    "purchasePricePerGramInChinaInDollars": 0.02852,
    "costPricePerGram": 0.036822,
    "salePriceInUkrainePerGramInDollars": 0.092
  },
  {
    "teaName": "Белый Облачный Чай Юнбай",
    "description": "Описание отсутствует.",
    "image": "Изображение отсутствует.",
    "category": "Неизвестно",
    "originCountry": "Страна происхождения отсутствует.",
    "teaStockInGrams": 900,
    "deliveryPricePerGramInDollars": 0.008302,
    "purchasePricePerGramInChinaInDollars": 0.05033,
    "costPricePerGram": 0.058632,
    "salePriceInUkrainePerGramInDollars": 0.1435
  },
  {
    "teaName": "Да Хун Пао Фруктовый",
    "description": "Описание отсутствует.",
    "image": "Изображение отсутствует.",
    "category": "Неизвестно",
    "originCountry": "Страна происхождения отсутствует.",
    "teaStockInGrams": 710,
    "deliveryPricePerGramInDollars": 0.008302,
    "purchasePricePerGramInChinaInDollars": 0.02445,
    "costPricePerGram": 0.032752,
    "salePriceInUkrainePerGramInDollars": 0.083325
  },
  {
    "teaName": "Бай Цзи Гуань 2022",
    "description": "Описание отсутствует.",
    "image": "Изображение отсутствует.",
    "category": "Неизвестно",
    "originCountry": "Страна происхождения отсутствует.",
    "teaStockInGrams": 190,
    "deliveryPricePerGramInDollars": 0.008302,
    "purchasePricePerGramInChinaInDollars": 0.1697,
    "costPricePerGram": 0.178002,
    "salePriceInUkrainePerGramInDollars": 0.456
  },
  {
    "teaName": "Шу Пуер Лао Шу Ча",
    "description": "Описание отсутствует.",
    "image": "Изображение отсутствует.",
    "category": "Неизвестно",
    "originCountry": "Страна происхождения отсутствует.",
    "teaStockInGrams": 700,
    "deliveryPricePerGramInDollars": 0.008302,
    "purchasePricePerGramInChinaInDollars": 0.04314,
    "costPricePerGram": 0.051442,
    "salePriceInUkrainePerGramInDollars": 0.0864
  },
  {
    "teaName": "Баотский чай BT5188",
    "description": "Описание отсутствует.",
    "image": "Изображение отсутствует.",
    "category": "Неизвестно",
    "originCountry": "Страна происхождения отсутствует.",
    "teaStockInGrams": 980,
    "deliveryPricePerGramInDollars": 0.008302,
    "purchasePricePerGramInChinaInDollars": 0.02301,
    "costPricePerGram": 0.031312,
    "salePriceInUkrainePerGramInDollars": 0.0992
  },
  {
    "teaName": "Сягуань СяоФа Точа 2023",
    "description": "Описание отсутствует.",
    "image": "Изображение отсутствует.",
    "category": "Неизвестно",
    "originCountry": "Страна происхождения отсутствует.",
    "teaStockInGrams": 1800,
    "deliveryPricePerGramInDollars": 0.008302,
    "purchasePricePerGramInChinaInDollars": 0.01854,
    "costPricePerGram": 0.026842,
    "salePriceInUkrainePerGramInDollars": 0.0765
  },
  {
    "teaName": "Тулин Феникс Т813",
    "description": "Описание отсутствует.",
    "image": "Изображение отсутствует.",
    "category": "Неизвестно",
    "originCountry": "Страна происхождения отсутствует.",
    "teaStockInGrams": 554,
    "deliveryPricePerGramInDollars": 0.008302,
    "purchasePricePerGramInChinaInDollars": 0.042,
    "costPricePerGram": 0.050302,
    "salePriceInUkrainePerGramInDollars": 0.12576
  },
  {
    "teaName": "Тулин Феникс Т812",
    "description": "Описание отсутствует.",
    "image": "Изображение отсутствует.",
    "category": "Неизвестно",
    "originCountry": "Страна происхождения отсутствует.",
    "teaStockInGrams": 700,
    "deliveryPricePerGramInDollars": 0.008302,
    "purchasePricePerGramInChinaInDollars": 0.03811,
    "costPricePerGram": 0.046412,
    "salePriceInUkrainePerGramInDollars": 0.10988
  },
  {
    "teaName": "Шу Пуер 8504",
    "description": "Описание отсутствует.",
    "image": "Изображение отсутствует.",
    "category": "Неизвестно",
    "originCountry": "Страна происхождения отсутствует.",
    "teaStockInGrams": 990,
    "deliveryPricePerGramInDollars": 0.008302,
    "purchasePricePerGramInChinaInDollars": 0.02127,
    "costPricePerGram": 0.029572,
    "salePriceInUkrainePerGramInDollars": 0.10767
  },
  {
    "teaName": "Шу пуэр Вино",
    "description": "Описание отсутствует.",
    "image": "Изображение отсутствует.",
    "category": "Неизвестно",
    "originCountry": "Страна происхождения отсутствует.",
    "teaStockInGrams": 180,
    "deliveryPricePerGramInDollars": 0.008302,
    "purchasePricePerGramInChinaInDollars": 0.07429,
    "costPricePerGram": 0.082592,
    "salePriceInUkrainePerGramInDollars": 0.16666
  }
]
